nansen/__init__.py
nansen/_version.py
nansen/main.py
nansen/core/gpx.py
nansen/io/gpx.py
nansen/utils/elevation.py
nansen/utils/smooth.py
nansen-0.3.0.dist-info/licenses/LICENSE
nansen-0.3.0.dist-info/METADATA
nansen-0.3.0.dist-info/WHEEL
nansen-0.3.0.dist-info/top_level.txt
nansen-0.3.0.dist-info/RECORD
