Metadata-Version: 2.4
Name: nansen
Version: 0.3.0
License-File: LICENSE
Requires-Dist: numpy>=1.20
Requires-Dist: gpxpy>=1.6.2
Requires-Dist: pandas>=1.3.0
Requires-Dist: matplotlib>=3.4.0
Requires-Dist: scipy>=1.7.0
Requires-Dist: geopy>=2.2.0
Requires-Dist: rich>=12.0.0
Requires-Dist: requests>=2.25.0
Requires-Dist: tqdm>=4.62.0
Dynamic: license-file
